proxy_tester/__init__.py
proxy_tester/__version__.py
proxy_tester/auto.py
proxy_tester/proxy_tester.py
proxy_tester/proxy_tester2.py
proxy_tester-0.18.dist-info/METADATA
proxy_tester-0.18.dist-info/WHEEL
proxy_tester-0.18.dist-info/entry_points.txt
proxy_tester-0.18.dist-info/top_level.txt
proxy_tester-0.18.dist-info/RECORD
